jwrite/__init__.py
jwrite/about.py
jwrite/error.py
jwrite/main_window.py
jwrite/views/About.ui
jwrite/views/Error.ui
jwrite/views/MainWindow.ui
jwrite-1.0.3.dist-info/WHEEL
jwrite-1.0.3.dist-info/LICENSE.md
jwrite-1.0.3.dist-info/METADATA
jwrite-1.0.3.dist-info/entry_points.txt
jwrite-1.0.3.dist-info/RECORD
